scriptlink/__init__.py
scriptlink/constants.py
scriptlink/holocv.py
scriptlink/scriptlink.py
scriptlink-0.0.2.dist-info/LICENSE
scriptlink-0.0.2.dist-info/METADATA
scriptlink-0.0.2.dist-info/WHEEL
scriptlink-0.0.2.dist-info/top_level.txt
scriptlink-0.0.2.dist-info/RECORD
