Metadata-Version: 2.1
Name: scriptlink
Version: 0.0.2
Summary: scriptlink
Home-page: UNKNOWN
Author: Lopht
Author-email: <bobjozeg@yahoo.com>
License: UNKNOWN
Keywords: python,scriptlink
Platform: UNKNOWN
Classifier: Development Status :: 3 - Alpha
Classifier: Intended Audience :: Education
Classifier: Programming Language :: Python :: 3
Classifier: Operating System :: Microsoft :: Windows
License-File: LICENSE
Requires-Dist: numpy
Requires-Dist: cv2
